{
  "description": "项目私有配置文件。此文件中的内容将覆盖 project.config.json 中的相同字段。项目的改动优先同步到此文件中。详见文档：https://developers.weixin.qq.com/miniprogram/dev/devtools/projectconfig.html",
  "projectname": "miniprogram-4",
  "setting": {
    "compileHotReLoad": true,
    "urlCheck": false
  },
  "libVersion": "2.27.1",
  "condition": {
    "plugin": {
      "list": []
    },
    "game": {
      "list": []
    },
    "gamePlugin": {
      "list": []
    },
    "miniprogram": {
      "list": [
        {
          "name": "add",
          "pathName": "pages/add/add",
          "query": "",
          "scene": null
        },
        {
          "name": "修改页面",
          "pathName": "pages/modify/modify",
          "query": "id=4e37263e635b9efb004dffaa2c219a4f",
          "scene": null
        },
        {
          "name": "图表",
          "pathName": "pages/statistics/statistics",
          "query": "",
          "scene": null
        },
        {
          "name": "我的",
          "pathName": "pages/mine/mine",
          "query": "",
          "scene": null
        },
        {
          "name": "pages/introduce/introduce",
          "pathName": "pages/introduce/introduce",
          "query": "",
          "scene": null
        }
      ]
    }
  }
}